[
  {
    "timestamp": "2026-04-02T05:21:59.068215+00:00",
    "total_on_page": 24,
    "alerts_sent": 0,
    "alerted_cats": []
  },
  {
    "timestamp": "2026-04-02T06:51:17.280508+00:00",
    "total_on_page": 24,
    "alerts_sent": 0,
    "alerted_cats": []
  },
  {
    "timestamp": "2026-04-02T08:11:19.001057+00:00",
    "total_on_page": 24,
    "alerts_sent": 0,
    "alerted_cats": []
  },
  {
    "timestamp": "2026-04-02T09:37:30.029499+00:00",
    "total_on_page": 24,
    "alerts_sent": 0,
    "alerted_cats": []
  },
  {
    "timestamp": "2026-04-02T10:59:57.296784+00:00",
    "total_on_page": 24,
    "alerts_sent": 0,
    "alerted_cats": []
  },
  {
    "timestamp": "2026-04-02T11:54:28.264956+00:00",
    "total_on_page": 24,
    "alerts_sent": 0,
    "alerted_cats": []
  },
  {
    "timestamp": "2026-04-02T13:43:50.579192+00:00",
    "total_on_page": 24,
    "alerts_sent": 0,
    "alerted_cats": []
  },
  {
    "timestamp": "2026-04-02T15:05:35.252196+00:00",
    "total_on_page": 24,
    "alerts_sent": 0,
    "alerted_cats": []
  },
  {
    "timestamp": "2026-04-02T16:32:14.390545+00:00",
    "total_on_page": 24,
    "alerts_sent": 0,
    "alerted_cats": []
  },
  {
    "timestamp": "2026-04-02T17:54:39.102867+00:00",
    "total_on_page": 24,
    "alerts_sent": 0,
    "alerted_cats": []
  },
  {
    "timestamp": "2026-04-02T19:06:14.099839+00:00",
    "total_on_page": 24,
    "alerts_sent": 0,
    "alerted_cats": []
  },
  {
    "timestamp": "2026-04-02T20:03:47.977805+00:00",
    "total_on_page": 24,
    "alerts_sent": 0,
    "alerted_cats": []
  },
  {
    "timestamp": "2026-04-02T21:05:06.376338+00:00",
    "total_on_page": 24,
    "alerts_sent": 0,
    "alerted_cats": []
  },
  {
    "timestamp": "2026-04-02T22:03:32.672050+00:00",
    "total_on_page": 24,
    "alerts_sent": 0,
    "alerted_cats": []
  },
  {
    "timestamp": "2026-04-02T23:01:59.687327+00:00",
    "total_on_page": 24,
    "alerts_sent": 0,
    "alerted_cats": []
  },
  {
    "timestamp": "2026-04-03T00:00:45.357298+00:00",
    "total_on_page": 24,
    "alerts_sent": 0,
    "alerted_cats": []
  },
  {
    "timestamp": "2026-04-03T03:35:51.364053+00:00",
    "total_on_page": 24,
    "alerts_sent": 0,
    "alerted_cats": []
  },
  {
    "timestamp": "2026-04-03T05:45:24.062567+00:00",
    "total_on_page": 24,
    "alerts_sent": 0,
    "alerted_cats": []
  },
  {
    "timestamp": "2026-04-03T07:21:09.463455+00:00",
    "total_on_page": 24,
    "alerts_sent": 0,
    "alerted_cats": []
  },
  {
    "timestamp": "2026-04-03T08:11:47.551465+00:00",
    "total_on_page": 24,
    "alerts_sent": 0,
    "alerted_cats": []
  },
  {
    "timestamp": "2026-04-03T09:31:02.575265+00:00",
    "total_on_page": 24,
    "alerts_sent": 0,
    "alerted_cats": []
  },
  {
    "timestamp": "2026-04-03T10:53:16.755723+00:00",
    "total_on_page": 24,
    "alerts_sent": 0,
    "alerted_cats": []
  },
  {
    "timestamp": "2026-04-03T11:43:13.636793+00:00",
    "total_on_page": 24,
    "alerts_sent": 0,
    "alerted_cats": []
  },
  {
    "timestamp": "2026-04-03T13:19:57.201918+00:00",
    "total_on_page": 24,
    "alerts_sent": 0,
    "alerted_cats": []
  },
  {
    "timestamp": "2026-04-03T14:24:15.719272+00:00",
    "total_on_page": 24,
    "alerts_sent": 0,
    "alerted_cats": []
  },
  {
    "timestamp": "2026-04-03T15:11:22.355444+00:00",
    "total_on_page": 24,
    "alerts_sent": 0,
    "alerted_cats": []
  },
  {
    "timestamp": "2026-04-03T16:04:06.309690+00:00",
    "total_on_page": 24,
    "alerts_sent": 0,
    "alerted_cats": []
  },
  {
    "timestamp": "2026-04-03T17:05:00.449280+00:00",
    "total_on_page": 24,
    "alerts_sent": 0,
    "alerted_cats": []
  },
  {
    "timestamp": "2026-04-03T18:03:52.935639+00:00",
    "total_on_page": 24,
    "alerts_sent": 0,
    "alerted_cats": []
  },
  {
    "timestamp": "2026-04-03T19:22:45.457555+00:00",
    "total_on_page": 24,
    "alerts_sent": 0,
    "alerted_cats": []
  },
  {
    "timestamp": "2026-04-03T20:01:31.811767+00:00",
    "total_on_page": 24,
    "alerts_sent": 0,
    "alerted_cats": []
  },
  {
    "timestamp": "2026-04-03T21:03:46.361678+00:00",
    "total_on_page": 24,
    "alerts_sent": 0,
    "alerted_cats": []
  },
  {
    "timestamp": "2026-04-03T21:59:11.600210+00:00",
    "total_on_page": 24,
    "alerts_sent": 0,
    "alerted_cats": []
  },
  {
    "timestamp": "2026-04-03T22:48:27.719346+00:00",
    "total_on_page": 24,
    "alerts_sent": 0,
    "alerted_cats": []
  },
  {
    "timestamp": "2026-04-03T23:41:52.348155+00:00",
    "total_on_page": 24,
    "alerts_sent": 0,
    "alerted_cats": []
  },
  {
    "timestamp": "2026-04-04T02:47:43.951290+00:00",
    "total_on_page": 24,
    "alerts_sent": 0,
    "alerted_cats": []
  },
  {
    "timestamp": "2026-04-04T04:58:19.827036+00:00",
    "total_on_page": 24,
    "alerts_sent": 0,
    "alerted_cats": []
  },
  {
    "timestamp": "2026-04-04T06:05:38.202644+00:00",
    "total_on_page": 24,
    "alerts_sent": 0,
    "alerted_cats": []
  },
  {
    "timestamp": "2026-04-04T07:34:10.139650+00:00",
    "total_on_page": 24,
    "alerts_sent": 0,
    "alerted_cats": []
  },
  {
    "timestamp": "2026-04-04T08:52:15.588539+00:00",
    "total_on_page": 24,
    "alerts_sent": 0,
    "alerted_cats": []
  },
  {
    "timestamp": "2026-04-04T09:49:07.723517+00:00",
    "total_on_page": 24,
    "alerts_sent": 0,
    "alerted_cats": []
  },
  {
    "timestamp": "2026-04-04T10:42:01.227042+00:00",
    "total_on_page": 24,
    "alerts_sent": 0,
    "alerted_cats": []
  },
  {
    "timestamp": "2026-04-04T11:35:50.700804+00:00",
    "total_on_page": 24,
    "alerts_sent": 0,
    "alerted_cats": []
  },
  {
    "timestamp": "2026-04-04T13:12:16.328315+00:00",
    "total_on_page": 24,
    "alerts_sent": 0,
    "alerted_cats": []
  },
  {
    "timestamp": "2026-04-04T14:06:22.304475+00:00",
    "total_on_page": 24,
    "alerts_sent": 0,
    "alerted_cats": []
  },
  {
    "timestamp": "2026-04-04T15:01:40.361071+00:00",
    "total_on_page": 24,
    "alerts_sent": 0,
    "alerted_cats": []
  },
  {
    "timestamp": "2026-04-04T15:57:22.319627+00:00",
    "total_on_page": 24,
    "alerts_sent": 0,
    "alerted_cats": []
  },
  {
    "timestamp": "2026-04-04T16:49:07.393894+00:00",
    "total_on_page": 24,
    "alerts_sent": 0,
    "alerted_cats": []
  },
  {
    "timestamp": "2026-04-04T17:39:32.862041+00:00",
    "total_on_page": 24,
    "alerts_sent": 0,
    "alerted_cats": []
  },
  {
    "timestamp": "2026-04-04T18:54:34.531388+00:00",
    "total_on_page": 24,
    "alerts_sent": 0,
    "alerted_cats": []
  },
  {
    "timestamp": "2026-04-04T19:37:33.838413+00:00",
    "total_on_page": 23,
    "alerts_sent": 0,
    "alerted_cats": []
  },
  {
    "timestamp": "2026-04-04T20:41:39.748703+00:00",
    "total_on_page": 23,
    "alerts_sent": 0,
    "alerted_cats": []
  },
  {
    "timestamp": "2026-04-04T21:38:41.413924+00:00",
    "total_on_page": 23,
    "alerts_sent": 0,
    "alerted_cats": []
  },
  {
    "timestamp": "2026-04-04T22:38:28.604631+00:00",
    "total_on_page": 23,
    "alerts_sent": 0,
    "alerted_cats": []
  },
  {
    "timestamp": "2026-04-04T23:38:45.507530+00:00",
    "total_on_page": 23,
    "alerts_sent": 0,
    "alerted_cats": []
  },
  {
    "timestamp": "2026-04-05T03:24:17.726723+00:00",
    "total_on_page": 23,
    "alerts_sent": 0,
    "alerted_cats": []
  },
  {
    "timestamp": "2026-04-05T05:26:23.081095+00:00",
    "total_on_page": 23,
    "alerts_sent": 0,
    "alerted_cats": []
  },
  {
    "timestamp": "2026-04-05T06:45:14.545992+00:00",
    "total_on_page": 23,
    "alerts_sent": 0,
    "alerted_cats": []
  },
  {
    "timestamp": "2026-04-05T07:58:08.431029+00:00",
    "total_on_page": 23,
    "alerts_sent": 0,
    "alerted_cats": []
  },
  {
    "timestamp": "2026-04-05T08:56:36.402159+00:00",
    "total_on_page": 23,
    "alerts_sent": 0,
    "alerted_cats": []
  },
  {
    "timestamp": "2026-04-05T09:50:36.701358+00:00",
    "total_on_page": 23,
    "alerts_sent": 0,
    "alerted_cats": []
  },
  {
    "timestamp": "2026-04-05T10:44:13.036717+00:00",
    "total_on_page": 23,
    "alerts_sent": 0,
    "alerted_cats": []
  },
  {
    "timestamp": "2026-04-05T11:37:35.613018+00:00",
    "total_on_page": 23,
    "alerts_sent": 0,
    "alerted_cats": []
  },
  {
    "timestamp": "2026-04-05T13:14:01.740879+00:00",
    "total_on_page": 23,
    "alerts_sent": 0,
    "alerted_cats": []
  },
  {
    "timestamp": "2026-04-05T14:07:19.471011+00:00",
    "total_on_page": 23,
    "alerts_sent": 0,
    "alerted_cats": []
  },
  {
    "timestamp": "2026-04-05T15:03:48.928427+00:00",
    "total_on_page": 23,
    "alerts_sent": 0,
    "alerted_cats": []
  },
  {
    "timestamp": "2026-04-05T15:58:35.489176+00:00",
    "total_on_page": 23,
    "alerts_sent": 0,
    "alerted_cats": []
  },
  {
    "timestamp": "2026-04-05T16:50:42.020244+00:00",
    "total_on_page": 23,
    "alerts_sent": 0,
    "alerted_cats": []
  },
  {
    "timestamp": "2026-04-05T17:39:28.666400+00:00",
    "total_on_page": 23,
    "alerts_sent": 0,
    "alerted_cats": []
  },
  {
    "timestamp": "2026-04-05T18:55:55.489037+00:00",
    "total_on_page": 23,
    "alerts_sent": 0,
    "alerted_cats": []
  },
  {
    "timestamp": "2026-04-05T19:39:54.493223+00:00",
    "total_on_page": 23,
    "alerts_sent": 0,
    "alerted_cats": []
  },
  {
    "timestamp": "2026-04-05T20:42:49.160379+00:00",
    "total_on_page": 23,
    "alerts_sent": 0,
    "alerted_cats": []
  },
  {
    "timestamp": "2026-04-05T21:40:01.712921+00:00",
    "total_on_page": 23,
    "alerts_sent": 0,
    "alerted_cats": []
  },
  {
    "timestamp": "2026-04-05T22:40:23.585262+00:00",
    "total_on_page": 23,
    "alerts_sent": 0,
    "alerted_cats": []
  },
  {
    "timestamp": "2026-04-05T23:42:07.344709+00:00",
    "total_on_page": 24,
    "alerts_sent": 1,
    "alerted_cats": [
      {
        "name": "Spike",
        "age_months": null,
        "url": "https://www.arthuranimalrescue.com/adoptables/spike"
      }
    ]
  },
  {
    "timestamp": "2026-04-06T03:27:30.034831+00:00",
    "total_on_page": 24,
    "alerts_sent": 0,
    "alerted_cats": []
  },
  {
    "timestamp": "2026-04-06T05:39:01.398977+00:00",
    "total_on_page": 24,
    "alerts_sent": 0,
    "alerted_cats": []
  },
  {
    "timestamp": "2026-04-06T07:56:24.470726+00:00",
    "total_on_page": 24,
    "alerts_sent": 0,
    "alerted_cats": []
  },
  {
    "timestamp": "2026-04-06T09:19:04.293697+00:00",
    "total_on_page": 24,
    "alerts_sent": 0,
    "alerted_cats": []
  },
  {
    "timestamp": "2026-04-06T10:39:28.932820+00:00",
    "total_on_page": 24,
    "alerts_sent": 0,
    "alerted_cats": []
  },
  {
    "timestamp": "2026-04-06T11:53:40.986142+00:00",
    "total_on_page": 24,
    "alerts_sent": 0,
    "alerted_cats": []
  },
  {
    "timestamp": "2026-04-06T13:26:08.646003+00:00",
    "total_on_page": 24,
    "alerts_sent": 0,
    "alerted_cats": []
  },
  {
    "timestamp": "2026-04-06T14:31:58.591800+00:00",
    "total_on_page": 24,
    "alerts_sent": 0,
    "alerted_cats": []
  },
  {
    "timestamp": "2026-04-06T15:56:09.319275+00:00",
    "total_on_page": 24,
    "alerts_sent": 0,
    "alerted_cats": []
  },
  {
    "timestamp": "2026-04-06T16:59:13.158174+00:00",
    "total_on_page": 24,
    "alerts_sent": 0,
    "alerted_cats": []
  },
  {
    "timestamp": "2026-04-06T17:57:30.713513+00:00",
    "total_on_page": 24,
    "alerts_sent": 0,
    "alerted_cats": []
  },
  {
    "timestamp": "2026-04-06T19:14:49.289431+00:00",
    "total_on_page": 25,
    "alerts_sent": 1,
    "alerted_cats": [
      {
        "name": "Ponzu",
        "age_months": null,
        "url": "https://www.arthuranimalrescue.com/adoptables/ponzu"
      }
    ]
  },
  {
    "timestamp": "2026-04-06T20:06:15.673669+00:00",
    "total_on_page": 25,
    "alerts_sent": 0,
    "alerted_cats": []
  },
  {
    "timestamp": "2026-04-06T21:07:16.321939+00:00",
    "total_on_page": 25,
    "alerts_sent": 0,
    "alerted_cats": []
  },
  {
    "timestamp": "2026-04-06T22:01:51.670300+00:00",
    "total_on_page": 25,
    "alerts_sent": 0,
    "alerted_cats": []
  },
  {
    "timestamp": "2026-04-06T23:06:35.983648+00:00",
    "total_on_page": 25,
    "alerts_sent": 0,
    "alerted_cats": []
  },
  {
    "timestamp": "2026-04-07T00:01:49.788361+00:00",
    "total_on_page": 25,
    "alerts_sent": 0,
    "alerted_cats": []
  },
  {
    "timestamp": "2026-04-07T03:38:52.354642+00:00",
    "total_on_page": 25,
    "alerts_sent": 0,
    "alerted_cats": []
  },
  {
    "timestamp": "2026-04-07T05:50:32.198636+00:00",
    "total_on_page": 25,
    "alerts_sent": 0,
    "alerted_cats": []
  },
  {
    "timestamp": "2026-04-07T07:43:13.949342+00:00",
    "total_on_page": 25,
    "alerts_sent": 0,
    "alerted_cats": []
  },
  {
    "timestamp": "2026-04-07T09:13:34.923621+00:00",
    "total_on_page": 25,
    "alerts_sent": 0,
    "alerted_cats": []
  },
  {
    "timestamp": "2026-04-07T10:35:18.703643+00:00",
    "total_on_page": 25,
    "alerts_sent": 0,
    "alerted_cats": []
  },
  {
    "timestamp": "2026-04-07T11:57:42.307902+00:00",
    "total_on_page": 25,
    "alerts_sent": 0,
    "alerted_cats": []
  },
  {
    "timestamp": "2026-04-07T13:54:03.277622+00:00",
    "total_on_page": 25,
    "alerts_sent": 0,
    "alerted_cats": []
  },
  {
    "timestamp": "2026-04-07T15:18:19.128180+00:00",
    "total_on_page": 25,
    "alerts_sent": 0,
    "alerted_cats": []
  }
]